wasla/__init__.py
wasla/builder.py
wasla/logger_middleware.py
wasla/middleware_interface.py
wasla/middleware_manager.py
wasla/request.py
wasla/router.py
wasla/routing_middleware.py
wasla/utils.py
wasla-0.0.1.dist-info/METADATA
wasla-0.0.1.dist-info/WHEEL
wasla-0.0.1.dist-info/licenses/LICENSE
wasla-0.0.1.dist-info/RECORD
