Metadata-Version: 2.4
Name: wasla
Version: 0.0.1
Summary: Wasla was developed to facilitate the build of events based systems that uses RabbitMQ as the message broker, wasla is built on aio_pika to represent the core of RabbitMQ connection, while wasla provides a mini framework for routing and middlewares. With the right configuration and a well structured routing map, you can publish an event to many consumers with just one line of code.
Project-URL: Homepage, https://github.com/MahmoudMetwalli/wasla
Project-URL: Issues, https://github.com/MahmoudMetwalli/wasla/issues
Author-email: Mahmoud Metwalli <mammkbih@gmail.com>
License-Expression: Apache-2.0
License-File: LICENSE
Classifier: Intended Audience :: Developers
Classifier: License :: OSI Approved :: Apache Software License
Classifier: Operating System :: OS Independent
Classifier: Programming Language :: Python :: 3
Classifier: Topic :: Software Development :: Libraries :: Python Modules
Requires-Python: >=3.9
Requires-Dist: aio-pika>=9.3.1
Requires-Dist: colorlog>=6.8.0
Requires-Dist: pydantic>=2.0.0
Requires-Dist: typing-extensions>=4.8.0
